tests/__init__.py
tests/test_frame.py
tests/test_io.py
tests/test_ops.py
gajaraj-1.0.dist-info/LICENSE
gajaraj-1.0.dist-info/METADATA
gajaraj-1.0.dist-info/WHEEL
gajaraj-1.0.dist-info/top_level.txt
gajaraj-1.0.dist-info/RECORD
