Metadata-Version: 2.1
Name: gajaraj
Version: 1.0
Summary: A Pandas alternative library in Python. Gajaraj aims to provide similar functionalities as Pandas, enabling users to perform data manipulation and analysis seamlessly.
Author: Akshat Shukla
Author-email: Akshatshukla317@gmail.com
Classifier: Programming Language :: Python :: 3
Classifier: License :: OSI Approved :: MIT License
Classifier: Operating System :: OS Independent
Requires-Python: >=3.6
License-File: LICENSE
Requires-Dist: pandas
